gini_py/__init__.py
gini_py/client.py
gini_py/models.py
gini_py/crypto/__init__.py
gini_py/crypto/encryption.py
gini_py-0.1.9.dist-info/licenses/LICENSE
test/__init__.py
test/test_client.py
gini_py-0.1.9.dist-info/METADATA
gini_py-0.1.9.dist-info/WHEEL
gini_py-0.1.9.dist-info/top_level.txt
gini_py-0.1.9.dist-info/RECORD
